{
  "doc_code": "СП 118.13330",
  "doc_name": "СП 118.13330",
  "extracted_pages": [
    7,
    35
  ],
  "references": [
    {
      "punkt": "СП 118.13330.2022 «Общественные здания и сооружения» (далее – СП 118.13330.2022)",
      "full_paragraph": "СП 118.13330.2022 «Общественные здания и сооружения» (далее – СП 118.13330.2022).",
      "page": 7,
      "doc_code": "СП 118.13330"
    },
    {
      "punkt": "п. 6.10 СП 118.13330.2022",
      "full_paragraph": "Входные площадки высотой от уровня тротуара более 0,45 м оборудуются ограждениями высотой не менее 0,8 м (п.п. 4.2.21 СП 1.13130.2020, п. 6.10 СП 118.13330.2022).",
      "page": 35,
      "doc_code": "СП 118.13330",
      "punkt_numbers": [
        "6.10"
      ]
    }
  ]
}